counted_float/__init__.py
counted_float/_core/__init__.py
counted_float/_core/_cli.py
counted_float/_core/benchmarking/__init__.py
counted_float/_core/benchmarking/counted_float/__init__.py
counted_float/_core/benchmarking/counted_float/_counted_float_benchmark.py
counted_float/_core/benchmarking/flops/__init__.py
counted_float/_core/benchmarking/flops/_array_generator.py
counted_float/_core/benchmarking/flops/_flops_benchmark_suite.py
counted_float/_core/benchmarking/flops/_flops_micro_benchmark.py
counted_float/_core/benchmarking/micro/__init__.py
counted_float/_core/benchmarking/micro/_micro_benchmark.py
counted_float/_core/compatibility/__init__.py
counted_float/_core/compatibility/_numba.py
counted_float/_core/counting/__init__.py
counted_float/_core/counting/_builtin_data.py
counted_float/_core/counting/_context_managers.py
counted_float/_core/counting/_counted_float.py
counted_float/_core/counting/_global_counter.py
counted_float/_core/counting/config/__init__.py
counted_float/_core/counting/config/_config.py
counted_float/_core/counting/config/_defaults.py
counted_float/_core/models/__init__.py
counted_float/_core/models/_base.py
counted_float/_core/models/_flop_counts.py
counted_float/_core/models/_flop_type.py
counted_float/_core/models/_flop_weights.py
counted_float/_core/models/_flops_benchmark_meta_data.py
counted_float/_core/models/_flops_benchmark_result.py
counted_float/_core/models/_flops_benchmark_type.py
counted_float/_core/models/_instruction_latencies.py
counted_float/_core/models/_micro_benchmark_result.py
counted_float/_core/utils/__init__.py
counted_float/_core/utils/_cpu_freq.py
counted_float/_core/utils/_formatting.py
counted_float/_core/utils/_geo_mean.py
counted_float/_core/utils/_latency.py
counted_float/_core/utils/_missing_data.py
counted_float/_core/utils/_rounding.py
counted_float/_core/utils/_timer.py
counted_float/benchmarking/__init__.py
counted_float/config/__init__.py
counted_float-1.0.3.dist-info/METADATA
counted_float-1.0.3.dist-info/WHEEL
counted_float-1.0.3.dist-info/entry_points.txt
counted_float-1.0.3.dist-info/licenses/LICENSE
counted_float-1.0.3.dist-info/RECORD
