Metadata-Version: 2.4
Name: counted-float
Version: 1.0.3
Summary: Count floating-point operations in Python code & benchmark relative flop costs.
Project-URL: Source, https://github.com/bertpl/counted-float
Project-URL: ChangeLog, https://github.com/bertpl/counted-float/blob/main/CHANGELOG.md
Project-URL: Issues, https://github.com/bertpl/counted-float/issues
Project-URL: Roadmap, https://github.com/bertpl/counted-float/milestones
License-File: LICENSE
Requires-Python: >=3.11
Requires-Dist: numpy>=1.20
Requires-Dist: psutil>=5.0
Requires-Dist: py-cpuinfo>=9.0.0
Requires-Dist: pydantic>=2.0.0
Requires-Dist: rich>=13.0.0
Provides-Extra: cli
Requires-Dist: click>=8.0.0; extra == 'cli'
Provides-Extra: numba
Requires-Dist: numba>=0.50; extra == 'numba'
